AsciiDotter/BrailleImage.py
AsciiDotter/BrailleSegment.py
AsciiDotter/Luminance.py
AsciiDotter/__init__.py
AsciiDotter/__main__.py
ascii_dotter/__init__.py
ascii_dotter/__main__.py
ascii_dotter/braille_image.py
ascii_dotter/braille_segment.py
ascii_dotter/luminance.py
AsciiDotter-2.1.0.dist-info/LICENSE
AsciiDotter-2.1.0.dist-info/METADATA
AsciiDotter-2.1.0.dist-info/WHEEL
AsciiDotter-2.1.0.dist-info/entry_points.txt
AsciiDotter-2.1.0.dist-info/top_level.txt
AsciiDotter-2.1.0.dist-info/RECORD
