Metadata-Version: 2.1
Name: AsciiDotter
Version: 2.1.0
Summary: CLI tool for turning images into ascii art.
Home-page: https://github.com/wciesialka/ascii-dotter
Author: Willow Ciesialka
Author-email: wciesialka@gmail.com
License: GPL-3.0
Keywords: python image ascii art
Platform: UNKNOWN
Classifier: License :: OSI Approved :: GNU Affero General Public License v3
Classifier: Programming Language :: Python :: 3
Classifier: Topic :: Artistic Software
Classifier: Operating System :: OS Independent
Requires-Python: >=3.8.10
Requires-Dist: Pillow (==8.4.0)
